{"error":null,"article":{"revision":787335529,"pageid":40431981,"title":"FemTechNet","canonicalurl":"https://en.wikipedia.org/wiki/FemTechNet","identifier":"FemTechNet","language":"en"},"article_parsed":{"reader":null,"date_read":"2014-04-21 00:00:00","is_date_normalized":true,"audio_file_titles":["File:En-FemTechNet-article.ogg"],"article_oldid":587825709,"oldid_quality":1,"oldURL":"https://en.wikipedia.org/w/index.php?title=FemTechNet&oldid=587825709"},"audio_files":[{"revision":-1,"pageid":-1,"metadataURL":null,"title":"File:En-FemTechNet-article.ogg","repository":"shared","downloadurl":"https://upload.wikimedia.org/wikipedia/commons/1/1f/En-FemTechNet-article.ogg","timestamp":"2014-04-22 06:06:51"}],"audio_file_parsed":{"reader":null,"date_read":"2014-04-21 00:00:00","is_date_normalized":true,"audio_file_titles":null,"article_oldid":587825709,"oldid_quality":2,"oldURL":null}}